dashai_test2_tabular_classification_package/__init__.py
dashai_test2_tabular_classification_package/sklearn_like_model.py
dashai_test2_tabular_classification_package/tabular_classification_model.py
dashai_test2_tabular_classification_package/tabular_classification_task.py
dashai_test2_tabular_classification_package/scikit_learn/decision_tree_classifier.py
dashai_test2_tabular_classification_package/scikit_learn/hist_gradient_boosting_classifier.py
dashai_test2_tabular_classification_package/scikit_learn/k_neighbors_classifier.py
dashai_test2_tabular_classification_package/scikit_learn/logistic_regression.py
dashai_test2_tabular_classification_package/scikit_learn/random_forest_classifier.py
dashai_test2_tabular_classification_package/scikit_learn/svc.py
dashai_test2_tabular_classification_package-0.1.6.dist-info/METADATA
dashai_test2_tabular_classification_package-0.1.6.dist-info/WHEEL
dashai_test2_tabular_classification_package-0.1.6.dist-info/entry_points.txt
dashai_test2_tabular_classification_package-0.1.6.dist-info/RECORD
