Metadata-Version: 2.3
Name: dashai_test2_tabular_classification_package
Version: 0.1.6
Summary: Tabular Classification Package
Author: DashAI team
Author-email: dashaisoftware@gmail.com
Keywords: DashAI,Dataloader,Model,Package,Task
Requires-Python: >=3.8
Requires-Dist: scikit-learn>=1.2.1
